Workbook

Sheet Executive Summary
D1: USD Conversion to INR | E1: 85
D2: EXECUTIVE SUMMARY
D3: Ownership Details | F3: Project Details
D4: Geography | E4: APAC | F4: Project ID
D5: SBU | F5: Project Name | G5: Climate & Disaster Resilience
D6: Customer | E6: Integra | F6: Win Classification | G6: New Win
D7: Customer Sub-Business | F7: Billing Model
D8: SBU Head | F8: Project Type | G8: AI ML
D9: Account Executive (Sales) | F9: Project Duration | G9: 12 Months
D10: Account Manager | F10: Delivery Manager
D11: Financial Summary | F11: Comments
D12: ROI Created & Included in Proposal | E12: YES | F12: <Use this section to share additional details about the account, strategic importance, assuptions etc.> | K12: 313488
D13: Services - Sales Price Guidance | E13: ='Module 3 During-Disaster Integr'!$BB$28 -> 1487808
D14: Services - Proposed Sales Price | E14: 1000000
D15: License Sales | E15: 0
D16: Total Sales Price | E16: =E14+E15 -> 1000000
D17: Employee Salary Cost | E17: 176126 | F17: Guidance Sales Price Guidance is as per the FY23 Sales Planning Sheet. Cost is as per Finance average costs. GM Guidance is 60% Offshore FTE Revenue Guidance is $6500
D18: Mgmt & Utilization Overheads (10%) | E18: 0
D19: Non-Billable Travel Cost | E19: 0
D20: Total Project Cost | E20: =SUM(E17:E19) -> 176126
D21: FTE Revenue - Onsite | E21: 0
D22: FTE Revenue - Offshore | E22: =E14/'Module 3 During-Disaster Integr'!$AZ$26 -> 4516.7118
D23: Gross Margin% | E23: 0.9
D24: Budget Gross Margin% | E24: 0.6
D25: Approval Needed | E25: YES | F25: Reason: Approval is needed if ROI isn't created OR Sale Price/margin are below guidance

Sheet Module 1 Engineering POD
A1: Activity / Month | D1: Month-1 | H1: Month-2 | L1: Month-3 | P1: Month-4 | T1: Month-5 | X1: Month-6 | AB1: Month-7 | AF1: Month-8 | AJ1: Month-9 | AN1: Month-10 | AR1: Month-11 | AV1: Month-12
A2: Consulting Phase + Data Access
A3: Data Ingestion Methodology
A4: Architecture Design Iterations
A5: Pipeline & Implementation & Architecture
A6: Architecture Hardening
A7: QA, QC, Integration & Testing
A11: Role / Month | B11: Geography | C11: ON/OFF | D11: Month-1 | H11: Month-2 | L11: Month-3 | P11: Month-4 | T11: Month-5 | X11: Month-6 | AB11: Month-7 | AF11: Month-8 | AJ11: Month-9 | AN11: Month-10 | AR11: Month-11 | AV11: Month-12 | AZ11: Total (mos) | BA11: Rate/Hr | BB11: Total Price
A12: Account Manager | B12: APAC | C12: Offshore | D12: 0.3 | H12: 0.3 | L12: 0.3 | AV12: 0.1 | AZ12: =SUM(D12:AY12) -> 1 | BA12: 40 | BB12: =AZ12*BA12*$BB$30 -> 6720
A13: Project Manager | B13: APAC | C13: Offshore | D13: 1 | H13: 1 | L13: 1 | P13: 0.75 | T13: 0.75 | X13: 0.75 | AB13: 0.5 | AF13: 0.5 | AJ13: 0.5 | AN13: 0.3 | AR13: 0.3 | AV13: 0.3 | AZ13: =SUM(D13:AY13) -> 7.65 | BA13: 40 | BB13: =AZ13*BA13*$BB$30 -> 51408
A14: Data Consultant | B14: APAC | C14: Offshore | AZ14: =SUM(D14:AY14) -> 0 | BA14: 40 | BB14: =AZ14*BA14*$BB$30 -> 0
A15: Lead Data Consultant | B15: APAC | C15: Offshore | D15: 1 | H15: 1 | L15: 1 | P15: 1 | T15: 1 | X15: 1 | AB15: 1 | AF15: 1 | AJ15: 1 | AN15: 0.5 | AR15: 0.5 | AV15: 0.5 | AZ15: =SUM(D15:AY15) -> 10.5 | BA15: 40 | BB15: =AZ15*BA15*$BB$30 -> 70560
A16: UX Design Lead | B16: APAC | C16: Offshore | P16: 0.75 | T16: 1 | X16: 1 | AB16: 1 | AF16: 0.75 | AJ16: 0.5 | AN16: 0.25 | AZ16: =SUM(D16:AY16) -> 5.25 | BA16: 40 | BB16: =AZ16*BA16*$BB$30 -> 35280
A17: UX Designer | B17: APAC | C17: Offshore | P17: 1 | T17: 1 | X17: 1 | AB17: 1 | AF17: 0.75 | AJ17: 0.5 | AN17: 0.25 | AZ17: =SUM(D17:AY17) -> 5.5 | BA17: 40 | BB17: =AZ17*BA17*$BB$30 -> 36960
A18: Lead Data Scientist | B18: APAC | C18: Offshore | D18: 1 | H18: 1 | L18: 1 | P18: 1 | T18: 1 | X18: 1 | AB18: 1 | AF18: 1 | AJ18: 1 | AN18: 0.75 | AR18: 0.75 | AV18: 0.5 | AZ18: =SUM(D18:AY18) -> 11 | BA18: 40 | BB18: =AZ18*BA18*$BB$30 -> 73920
A19: Data Scientist | B19: APAC | C19: Offshore | D19: 1 | H19: 1 | L19: 1 | P19: 1 | T19: 1 | X19: 1 | AB19: 1 | AF19: 1 | AJ19: 0.75 | AN19: 0.5 | AR19: 0.25 | AV19: 0.25 | AZ19: =SUM(D19:AY19) -> 9.75 | BA19: 40 | BB19: =AZ19*BA19*$BB$30 -> 65520
A20: Technical Lead | B20: APAC | C20: Offshore | D20: 1 | H20: 1 | L20: 1 | P20: 1 | T20: 1 | X20: 1 | AB20: 1 | AF20: 1 | AJ20: 1 | AN20: 0.75 | AR20: 0.5 | AV20: 0.3 | AZ20: =SUM(D20:AY20) -> 10.55 | BA20: 40 | BB20: =AZ20*BA20*$BB$30 -> 70896
A21: Senior Developer | B21: APAC | C21: Offshore | H21: 2 | L21: 2 | P21: 2 | T21: 2 | X21: 2 | AB21: 1 | AF21: 1 | AJ21: 1 | AN21: 1 | AR21: 1 | AV21: 0.75 | AZ21: =SUM(D21:AY21) -> 15.75 | BA21: 40 | BB21: =AZ21*BA21*$BB$30 -> 105840
A22: Developer | B22: APAC | C22: Offshore | X22: 1 | AB22: 1 | AF22: 1 | AJ22: 1 | AN22: 1 | AR22: 1 | AV22: 1 | AZ22: =SUM(D22:AY22) -> 7 | BA22: 40 | BB22: =AZ22*BA22*$BB$30 -> 47040
A23: QA Tester | B23: APAC | C23: Offshore | AJ23: 1 | AN23: 1 | AR23: 1 | AV23: 0.75 | AZ23: =SUM(D23:AY23) -> 3.75 | BA23: 40 | BB23: =AZ23*BA23*$BB$30 -> 25200
B24: APAC | AZ24: =SUM(D24:AY24) -> 0 | BA24: 0 | BB24: =AZ24*BA24*$BB$30 -> 0
B25: APAC | AZ25: =SUM(D25:AY25) -> 0 | BA25: 0 | BB25: =AZ25*BA25*$BB$30 -> 0
A26: Total FTE Man Months | D26: =SUM(D12:D25) -> 5.3 | H26: =SUM(H12:H25) -> 7.3 | L26: =SUM(L12:L25) -> 7.3 | P26: =SUM(P12:P25) -> 8.5 | T26: =SUM(T12:T25) -> 8.75 | X26: =SUM(X12:X25) -> 9.75 | AB26: =SUM(AB12:AB25) -> 8.5 | AF26: =SUM(AF12:AF25) -> 8 | AJ26: =SUM(AJ12:AJ25) -> 8.25 | AN26: =SUM(AN12:AN25) -> 6.3 | AR26: =SUM(AR12:AR25) -> 5.3 | AV26: =SUM(AV12:AV25) -> 4.45 | AZ26: =SUM(AZ12:AZ25) -> 87.7 | BB26: =SUM(BB12:BB25) -> 589344
A27: *Geography is taken directly from Executive Summary sheet. Please update it in Executive Summary sheet to change Geo.
AZ28: Total Billing in USD | BB28: =BB26 -> 589344
AZ29: Total Billing in INR | BB29: ='Executive Summary'!$E$1*BB28 -> 50094240
AZ30: Billable Hours per Month (assumption) | BB30: 168
A33: Budget Summary based on the Final Pricing (Cell#E14 in Executive Summary Tab)
A34: Budget Parameter | D34: Consulting | H34: Design | L34: Analytics | P34: Technology | T34: QA | X34: Del EX
A35: Effort (PM) | D35: 10.5 | H35: 10.75 | L35: 20.75 | P35: 17.55 | T35: 3.75 | X35: 7.65
A36: Revenue (USD) | D36: =(D35/$AZ$26)*'Executive Summary'!$E$14 -> 119726.34 | H36: =(H35/$AZ$26)*'Executive Summary'!$E$14 -> 122576.97 | L36: =(L35/$AZ$26)*'Executive Summary'!$E$14 -> 236602.05 | P36: =(P35/$AZ$26)*'Executive Summary'!$E$14 -> 200114.03 | T36: =(T35/$AZ$26)*'Executive Summary'!$E$14 -> 42759.407 | X36: =(X35/$AZ$26)*'Executive Summary'!$E$14 -> 87229.19
A40: Budget Break-up by Month
A41: ON/OFF | D41: Month-1 | H41: Month-2 | L41: Month-3 | P41: Month-4 | T41: Month-5 | X41: Month-6 | AB41: Month-7 | AF41: Month-8 | AJ41: Month-9 | AN41: Month-10 | AR41: Month-11 | AV41: Month-12 | AZ41: Total | BA41: Balance
A42: Budget | D42: =(D26/$AZ$26)*'Executive Summary'!$E$14 -> 60433.295 | H42: =(H26/$AZ$26)*'Executive Summary'!$E$14 -> 83238.312 | L42: =(L26/$AZ$26)*'Executive Summary'!$E$14 -> 83238.312 | P42: =(P26/$AZ$26)*'Executive Summary'!$E$14 -> 96921.323 | T42: =(T26/$AZ$26)*'Executive Summary'!$E$14 -> 99771.95 | X42: =(X26/$AZ$26)*'Executive Summary'!$E$14 -> 111174.46 | AB42: =(AB26/$AZ$26)*'Executive Summary'!$E$14 -> 96921.323 | AF42: =(AF26/$AZ$26)*'Executive Summary'!$E$14 -> 91220.068 | AJ42: =(AJ26/$AZ$26)*'Executive Summary'!$E$14 -> 94070.696 | AN42: =(AN26/$AZ$26)*'Executive Summary'!$E$14 -> 71835.804 | AR42: =(AR26/$AZ$26)*'Executive Summary'!$E$14 -> 60433.295 | AV42: =(AV26/$AZ$26)*'Executive Summary'!$E$14 -> 50741.163 | AZ42: =SUM(D42:AY42) -> 1000000
A43: Accrual | AZ43: =SUM(D43:AY43) -> 0 | BA43: =AZ42-AZ43 -> 1000000
A44: Invoice | AZ44: =SUM(D44:AY44) -> 0 | BA44: =AZ42-AZ44 -> 1000000

Sheet Module 1 Cost Guidance
A4: Module 1
B5: Line Item | C5: Cost | D5: Comments
B6: #FTEs | C6: NA
B7: Resource Load Cost (as per resource load plan) | C7: ='Module 1 Engineering POD'!$BB$28 -> 589344
B8: SG & A, Project Risk Factors & Other Overheads etc. (25%) | C8: =C7*0.15 -> 88401.6
B9: Total Development Cost (sales guidance) | C9: =C7+C8 -> 677745.6
B11: Integrated Data Engineering Module for all the 3 Hazards | C11: 491366
B12: Integrated Data Engineering Module for all the 3 Hazards | C12: =C11 -> 491366
B13: Annual Upkeep & Maintenance | C13: =C12*0.275 -> 135125.65
B16: AWS Cloud Cost | C16: ='Cloud Infra Estimate'!$E$15 -> 216000
B17: Final AWS Cloud Cost (rounded off for minor variations) | C17: =C16 -> 216000
B21: Final Cost Structure
B23: Category | C23: Sub-Category | D23: Year-1 | E23: Year-2 | F23: Year-3 | G23: Total
B24: Integrated Pre-Disaster Module for all the 3 Hazards | C24: One-time Development (professional fee) | D24: =C12 -> 491366 | G24: =D24 -> 491366
C25: Annual Upkeep & Maintenance | D25: =C13*0.5 -> 67562.825 | E25: =C13 -> 135125.65 | F25: =C13 -> 135125.65 | G25: =SUM(D25:F25) -> 337814.12
C26: Total | D26: =D24+D25 -> 558928.82 | E26: =E25 -> 135125.65 | F26: =F25 -> 135125.65 | G26: =D24*0.275 -> 135125.65
B27: Cloud Infrastructure Costs | C27: AWS Costs | D27: ='Cloud Infra Estimate'!$E$15 -> 216000 | E27: ='Cloud Infra Estimate'!$E$15 -> 216000 | F27: ='Cloud Infra Estimate'!$E$15 -> 216000 | G27: =SUM(D27:F27) -> 648000
C28: Total | D28: =D27 -> 216000 | E28: =E27 -> 216000 | F28: =F27 -> 216000 | G28: =SUM(D28:F28) -> 648000
B29: TOTAL | D29: =D26+D28 -> 774928.82 | E29: =E26+E28 -> 351125.65 | F29: =F26+F28 -> 351125.65 | G29: =G26+G28 -> 783125.65

Sheet Module 2 Pre-Disaster Integrate
A1: Activity / Month | D1: Month-1 | H1: Month-2 | L1: Month-3 | P1: Month-4 | T1: Month-5 | X1: Month-6 | AB1: Month-7 | AF1: Month-8 | AJ1: Month-9 | AN1: Month-10 | AR1: Month-11 | AV1: Month-12
A2: Requirements and project planning
A3: Data and methodology review
A4: Workshops with stakeholders
A5: Development
A6: Integration Development (APIs)
A7: Testing (Ground-Truth Data or On-Ground)
A8: UAT and Go-Live
A11: Role / Month | B11: Geography | C11: ON/OFF | D11: Month-1 | H11: Month-2 | L11: Month-3 | P11: Month-4 | T11: Month-5 | X11: Month-6 | AB11: Month-7 | AF11: Month-8 | AJ11: Month-9 | AN11: Month-10 | AR11: Month-11 | AV11: Month-12 | AZ11: Total (mos) | BA11: Rate/Hr | BB11: Total Price
A12: Account Manager | B12: APAC | C12: Offshore | D12: 0.5 | H12: 0.5 | L12: 0.5 | P12: 0.2 | T12: 0.2 | X12: 0.2 | AB12: 0.2 | AF12: 0.2 | AJ12: 0.1 | AN12: 0.1 | AR12: 0.2 | AV12: 0.2 | AZ12: =SUM(D12:AY12) -> 3.1 | BA12: 40 | BB12: =AZ12*BA12*$BB$30 -> 20832
A13: Project Manager | B13: APAC | C13: Offshore | D13: 1 | H13: 1 | L13: 1 | P13: 1 | T13: 1 | X13: 1 | AB13: 1 | AF13: 1 | AJ13: 1 | AN13: 1 | AR13: 1 | AV13: 1 | AZ13: =SUM(D13:AY13) -> 12 | BA13: 40 | BB13: =AZ13*BA13*$BB$30 -> 80640
A14: Data Consultant | B14: APAC | C14: Offshore | D14: 1 | H14: 1 | L14: 1 | P14: 1 | T14: 1 | X14: 1 | AB14: 1 | AF14: 1 | AJ14: 1 | AN14: 1 | AR14: 1 | AV14: 1 | AZ14: =SUM(D14:AY14) -> 12 | BA14: 40 | BB14: =AZ14*BA14*$BB$30 -> 80640
A15: Lead Data Consultant | B15: APAC | C15: Offshore | D15: 1 | H15: 1 | L15: 1 | P15: 1 | T15: 1 | X15: 1 | AB15: 1 | AF15: 1 | AJ15: 1 | AN15: 1 | AR15: 1 | AV15: 1 | AZ15: =SUM(D15:AY15) -> 12 | BA15: 40 | BB15: =AZ15*BA15*$BB$30 -> 80640
A16: UX Design Lead | B16: APAC | C16: Offshore | P16: 1 | T16: 1 | X16: 1 | AB16: 1 | AF16: 1 | AJ16: 1 | AN16: 1 | AR16: 0.75 | AV16: 0.3 | AZ16: =SUM(D16:AY16) -> 8.05 | BA16: 40 | BB16: =AZ16*BA16*$BB$30 -> 54096
A17: UX Designer | B17: APAC | C17: Offshore | P17: 1 | T17: 1 | X17: 1 | AB17: 1 | AF17: 1 | AJ17: 1 | AN17: 1 | AR17: 0.75 | AZ17: =SUM(D17:AY17) -> 7.75 | BA17: 40 | BB17: =AZ17*BA17*$BB$30 -> 52080
A18: Lead Data Scientist | B18: APAC | C18: Offshore | D18: 1 | H18: 1 | L18: 1 | P18: 1 | T18: 2 | X18: 2 | AB18: 2 | AF18: 2 | AJ18: 1 | AN18: 1 | AR18: 1 | AV18: 1 | AZ18: =SUM(D18:AY18) -> 16 | BA18: 40 | BB18: =AZ18*BA18*$BB$30 -> 107520
A19: Data Scientist | B19: APAC | C19: Offshore | D19: 2 | H19: 2 | L19: 2 | P19: 2 | T19: 2 | X19: 2 | AB19: 2 | AF19: 2 | AJ19: 2 | AN19: 2 | AR19: 2 | AV19: 2 | AZ19: =SUM(D19:AY19) -> 24 | BA19: 40 | BB19: =AZ19*BA19*$BB$30 -> 161280
A20: Technical Lead | B20: APAC | C20: Offshore | D20: 1 | H20: 1 | L20: 1 | P20: 1 | T20: 1 | X20: 1 | AB20: 1 | AF20: 1 | AJ20: 1 | AN20: 1 | AR20: 1 | AV20: 1 | AZ20: =SUM(D20:AY20) -> 12 | BA20: 40 | BB20: =AZ20*BA20*$BB$30 -> 80640
A21: Senior Developer | B21: APAC | C21: Offshore | H21: 2 | L21: 2 | P21: 2 | T21: 2 | X21: 2 | AB21: 1 | AF21: 1 | AJ21: 1 | AN21: 1 | AR21: 1 | AV21: 1 | AZ21: =SUM(D21:AY21) -> 16 | BA21: 40 | BB21: =AZ21*BA21*$BB$30 -> 107520
A22: Developer | B22: APAC | C22: Offshore | H22: 1 | L22: 1 | P22: 1 | T22: 1 | X22: 1 | AB22: 1 | AF22: 1 | AJ22: 2 | AN22: 1.5 | AR22: 1.5 | AV22: 1.3 | AZ22: =SUM(D22:AY22) -> 13.3 | BA22: 40 | BB22: =AZ22*BA22*$BB$30 -> 89376
A23: QA Tester | B23: APAC | C23: Offshore | AB23: 1 | AF23: 1 | AJ23: 2 | AN23: 2 | AR23: 2 | AV23: 2 | AZ23: =SUM(D23:AY23) -> 10 | BA23: 40 | BB23: =AZ23*BA23*$BB$30 -> 67200
B24: APAC | AZ24: =SUM(D24:AY24) -> 0 | BA24: 0 | BB24: =AZ24*BA24*$BB$30 -> 0
B25: APAC | AZ25: =SUM(D25:AY25) -> 0 | BA25: 0 | BB25: =AZ25*BA25*$BB$30 -> 0
A26: Total FTE Man Months | D26: =SUM(D12:D25) -> 7.5 | H26: =SUM(H12:H25) -> 10.5 | L26: =SUM(L12:L25) -> 10.5 | P26: =SUM(P12:P25) -> 12.2 | T26: =SUM(T12:T25) -> 13.2 | X26: =SUM(X12:X25) -> 13.2 | AB26: =SUM(AB12:AB25) -> 13.2 | AF26: =SUM(AF12:AF25) -> 13.2 | AJ26: =SUM(AJ12:AJ25) -> 14.1 | AN26: =SUM(AN12:AN25) -> 13.6 | AR26: =SUM(AR12:AR25) -> 13.2 | AV26: =SUM(AV12:AV25) -> 11.8 | AZ26: =SUM(AZ12:AZ25) -> 146.2 | BB26: =SUM(BB12:BB25) -> 982464
A27: *Geography is taken directly from Executive Summary sheet. Please update it in Executive Summary sheet to change Geo.
AZ28: Total Billing in USD | BB28: =BB26 -> 982464
AZ29: Total Billing in INR | BB29: ='Executive Summary'!$E$1*BB28 -> 83509440
AZ30: Billable Hours per Month (assumption) | BB30: 168
A33: Budget Summary based on the Final Pricing (Cell#E14 in Executive Summary Tab)
A34: Budget Parameter | D34: Consulting | H34: Design | L34: Analytics | P34: Technology | T34: QA | X34: Del EX
A35: Effort (PM) | D35: 24 | H35: 15.8 | L35: 40 | P35: 25.3 | T35: 10 | X35: 12
A36: Revenue (USD) | D36: =(D35/$AZ$26)*'Executive Summary'!$E$14 -> 164158.69 | H36: =(H35/$AZ$26)*'Executive Summary'!$E$14 -> 108071.14 | L36: =(L35/$AZ$26)*'Executive Summary'!$E$14 -> 273597.81 | P36: =(P35/$AZ$26)*'Executive Summary'!$E$14 -> 173050.62 | T36: =(T35/$AZ$26)*'Executive Summary'!$E$14 -> 68399.453 | X36: =(X35/$AZ$26)*'Executive Summary'!$E$14 -> 82079.343
A40: Budget Break-up by Month
A41: ON/OFF | D41: Month-1 | H41: Month-2 | L41: Month-3 | P41: Month-4 | T41: Month-5 | X41: Month-6 | AB41: Month-7 | AF41: Month-8 | AJ41: Month-9 | AN41: Month-10 | AR41: Month-11 | AV41: Month-12 | AZ41: Total | BA41: Balance
A42: Budget | D42: =(D26/$AZ$26)*'Executive Summary'!$E$14 -> 51299.59 | H42: =(H26/$AZ$26)*'Executive Summary'!$E$14 -> 71819.425 | L42: =(L26/$AZ$26)*'Executive Summary'!$E$14 -> 71819.425 | P42: =(P26/$AZ$26)*'Executive Summary'!$E$14 -> 83447.332 | T42: =(T26/$AZ$26)*'Executive Summary'!$E$14 -> 90287.278 | X42: =(X26/$AZ$26)*'Executive Summary'!$E$14 -> 90287.278 | AB42: =(AB26/$AZ$26)*'Executive Summary'!$E$14 -> 90287.278 | AF42: =(AF26/$AZ$26)*'Executive Summary'!$E$14 -> 90287.278 | AJ42: =(AJ26/$AZ$26)*'Executive Summary'!$E$14 -> 96443.228 | AN42: =(AN26/$AZ$26)*'Executive Summary'!$E$14 -> 93023.256 | AR42: =(AR26/$AZ$26)*'Executive Summary'!$E$14 -> 90287.278 | AV42: =(AV26/$AZ$26)*'Executive Summary'!$E$14 -> 80711.354 | AZ42: =SUM(D42:AY42) -> 1000000
A43: Accrual | AZ43: =SUM(D43:AY43) -> 0 | BA43: =AZ42-AZ43 -> 1000000
A44: Invoice | AZ44: =SUM(D44:AY44) -> 0 | BA44: =AZ42-AZ44 -> 1000000

Sheet Module 2 Cost Guidance
A4: Module 2
B5: Line Item | C5: Cost | D5: Comments
B6: #FTEs | C6: NA
B7: Resource Load Cost (as per resource load plan) | C7: ='Module 2 Pre-Disaster Integrate'!$BB$28 -> 982464
B8: SG & A, Project Risk Factors & Other Overheads etc. (25%) | C8: =C7*0.15 -> 147369.6
B9: Total Development Cost (sales guidance) | C9: =C7+C8 -> 1129833.6
B11: Pre-Disaster Integrated POD for all the 3 Hazards | C11: 807024
B12: Integrated Data Engineering Module for all the 3 Hazards | C12: =C11 -> 807024
B13: Annual Upkeep & Maintenance | C13: =C12*0.24 -> 193685.76
B16: AWS Cloud Cost | C16: ='Cloud Infra Estimate'!$F$15 -> 353500
B17: Final AWS Cloud Cost (rounded off for minor variations) | C17: =C16 -> 353500
B21: Final Cost Structure
B23: Category | C23: Sub-Category | D23: Year-1 | E23: Year-2 | F23: Year-3 | G23: Total
B24: Integrated Pre-Disaster Module for all the 3 Hazards | C24: One-time Development (professional fee) | D24: =C12 -> 807024 | G24: =D24 -> 807024
C25: Annual Upkeep & Maintenance | D25: =C13*0.5 -> 96842.88 | E25: =C13 -> 193685.76 | F25: =C13 -> 193685.76 | G25: =SUM(D25:F25) -> 484214.4
C26: Total | D26: =D24+D25 -> 903866.88 | E26: =E25 -> 193685.76 | F26: =F25 -> 193685.76 | G26: =D24*0.275 -> 221931.6
B27: Cloud Infrastructure Costs | C27: AWS Costs | D27: ='Cloud Infra Estimate'!$F$15 -> 353500 | E27: ='Cloud Infra Estimate'!$F$15 -> 353500 | F27: ='Cloud Infra Estimate'!$F$15 -> 353500 | G27: =SUM(D27:F27) -> 1060500
C28: Total | D28: =D27 -> 353500 | E28: =E27 -> 353500 | F28: =F27 -> 353500 | G28: =SUM(D28:F28) -> 1060500
B29: TOTAL | D29: =D26+D28 -> 1257366.9 | E29: =E26+E28 -> 547185.76 | F29: =F26+F28 -> 547185.76 | G29: =G26+G28 -> 1282431.6

Sheet Module 3 During-Disaster Integr
A1: Activity / Month | D1: Month-1 | H1: Month-2 | L1: Month-3 | P1: Month-4 | T1: Month-5 | X1: Month-6 | AB1: Month-7 | AF1: Month-8 | AJ1: Month-9 | AN1: Month-10 | AR1: Month-11 | AV1: Month-12
A2: Requirements and project planning
A3: Data and methodology review
A4: Workshops with stakeholders
A5: Development
A6: Integration Development (APIs)
A7: Testing (Ground-Truth Data or On-Ground)
A8: UAT and Go-Live
A11: Role / Month | B11: Geography | C11: ON/OFF | D11: Month-1 | H11: Month-2 | L11: Month-3 | P11: Month-4 | T11: Month-5 | X11: Month-6 | AB11: Month-7 | AF11: Month-8 | AJ11: Month-9 | AN11: Month-10 | AR11: Month-11 | AV11: Month-12 | AZ11: Total (mos) | BA11: Rate/Hr | BB11: Total Price
A12: Account Manager | B12: APAC | C12: Offshore | D12: 0.5 | H12: 0.5 | L12: 0.5 | P12: 0.2 | T12: 0.2 | X12: 0.2 | AB12: 0.2 | AF12: 0.2 | AJ12: 0.2 | AN12: 0.2 | AR12: 0.2 | AV12: 0.2 | AZ12: =SUM(D12:AY12) -> 3.3 | BA12: 40 | BB12: =AZ12*BA12*$BB$30 -> 22176
A13: Project Manager | B13: APAC | C13: Offshore | D13: 1 | H13: 1 | L13: 1 | P13: 1 | T13: 1 | X13: 1 | AB13: 1 | AF13: 1 | AJ13: 1 | AN13: 1 | AR13: 1 | AV13: 1 | AZ13: =SUM(D13:AY13) -> 12 | BA13: 40 | BB13: =AZ13*BA13*$BB$30 -> 80640
A14: Data Consultant | B14: APAC | C14: Offshore | D14: 2 | H14: 2 | L14: 2 | P14: 2 | T14: 2 | X14: 2 | AB14: 2 | AF14: 2 | AJ14: 2 | AN14: 2 | AR14: 2 | AV14: 2 | AZ14: =SUM(D14:AY14) -> 24 | BA14: 40 | BB14: =AZ14*BA14*$BB$30 -> 161280
A15: Lead Data Consultant | B15: APAC | C15: Offshore | D15: 2 | H15: 2 | L15: 2 | P15: 2 | T15: 2 | X15: 2 | AB15: 1.5 | AF15: 1.5 | AJ15: 1.5 | AN15: 1.5 | AR15: 1.5 | AV15: 1 | AZ15: =SUM(D15:AY15) -> 20.5 | BA15: 40 | BB15: =AZ15*BA15*$BB$30 -> 137760
A16: UX Design Lead | B16: APAC | C16: Offshore | P16: 1 | T16: 1 | X16: 1 | AB16: 1 | AF16: 1 | AJ16: 1 | AN16: 1 | AR16: 1 | AV16: 0.8 | AZ16: =SUM(D16:AY16) -> 8.8 | BA16: 40 | BB16: =AZ16*BA16*$BB$30 -> 59136
A17: UX Designer | B17: APAC | C17: Offshore | P17: 1 | T17: 1 | X17: 1 | AB17: 1 | AF17: 1 | AJ17: 1 | AN17: 1 | AR17: 1 | AV17: 0.8 | AZ17: =SUM(D17:AY17) -> 8.8 | BA17: 40 | BB17: =AZ17*BA17*$BB$30 -> 59136
A18: Lead Data Scientist | B18: APAC | C18: Offshore | D18: 2 | H18: 2 | L18: 2 | P18: 2 | T18: 2 | X18: 2 | AB18: 2 | AF18: 2 | AJ18: 2 | AN18: 2 | AR18: 2 | AV18: 2 | AZ18: =SUM(D18:AY18) -> 24 | BA18: 40 | BB18: =AZ18*BA18*$BB$30 -> 161280
A19: Data Scientist | B19: APAC | C19: Offshore | D19: 2 | H19: 2 | L19: 2 | P19: 3 | T19: 3 | X19: 3 | AB19: 3 | AF19: 3 | AJ19: 3 | AN19: 3 | AR19: 2 | AV19: 2 | AZ19: =SUM(D19:AY19) -> 31 | BA19: 40 | BB19: =AZ19*BA19*$BB$30 -> 208320
A20: Technical Lead | B20: APAC | C20: Offshore | D20: 2 | H20: 2 | L20: 2 | P20: 2 | T20: 2 | X20: 1 | AB20: 1 | AF20: 1 | AJ20: 1 | AN20: 1 | AR20: 1 | AV20: 1 | AZ20: =SUM(D20:AY20) -> 17 | BA20: 40 | BB20: =AZ20*BA20*$BB$30 -> 114240
A21: Senior Developer | B21: APAC | C21: Offshore | D21: 2 | H21: 2 | L21: 2 | P21: 2 | T21: 2 | X21: 2 | AB21: 2 | AF21: 2 | AJ21: 1 | AN21: 1 | AR21: 1 | AV21: 1 | AZ21: =SUM(D21:AY21) -> 20 | BA21: 40 | BB21: =AZ21*BA21*$BB$30 -> 134400
A22: Developer | B22: APAC | C22: Offshore | D22: 3 | H22: 3 | L22: 3 | P22: 3 | T22: 2 | X22: 2 | AB22: 2 | AF22: 2 | AJ22: 2 | AN22: 2 | AR22: 2 | AV22: 2 | AZ22: =SUM(D22:AY22) -> 28 | BA22: 40 | BB22: =AZ22*BA22*$BB$30 -> 188160
A23: DevOps Engineer | B23: APAC | C23: Offshore | D23: 1 | H23: 1 | L23: 1 | P23: 1 | AJ23: 1 | AN23: 1 | AR23: 1 | AV23: 1 | AZ23: =SUM(D23:AY23) -> 8 | BA23: 40 | BB23: =AZ23*BA23*$BB$30 -> 53760
A24: QA Tester | B24: APAC | C24: Offshore | T24: 2 | X24: 2 | AB24: 2 | AF24: 2 | AJ24: 2 | AN24: 2 | AR24: 2 | AV24: 2 | AZ24: =SUM(D24:AY24) -> 16 | BA24: 40 | BB24: =AZ24*BA24*$BB$30 -> 107520
B25: APAC | AZ25: =SUM(D25:AY25) -> 0 | BA25: 0 | BB25: =AZ25*BA25*$BB$30 -> 0
A26: Total FTE Man Months | D26: =SUM(D12:D25) -> 17.5 | H26: =SUM(H12:H25) -> 17.5 | L26: =SUM(L12:L25) -> 17.5 | P26: =SUM(P12:P25) -> 20.2 | T26: =SUM(T12:T25) -> 20.2 | X26: =SUM(X12:X25) -> 19.2 | AB26: =SUM(AB12:AB25) -> 18.7 | AF26: =SUM(AF12:AF25) -> 18.7 | AJ26: =SUM(AJ12:AJ25) -> 18.7 | AN26: =SUM(AN12:AN25) -> 18.7 | AR26: =SUM(AR12:AR25) -> 17.7 | AV26: =SUM(AV12:AV25) -> 16.8 | AZ26: =SUM(AZ12:AZ25) -> 221.4 | BB26: =SUM(BB12:BB25) -> 1487808
A27: *Geography is taken directly from Executive Summary sheet. Please update it in Executive Summary sheet to change Geo.
AZ28: Total Billing in USD | BB28: =BB26 -> 1487808
AZ29: Total Billing in INR | BB29: ='Executive Summary'!$E$1*BB28 -> 126463680
AZ30: Billable Hours per Month (assumption) | BB30: 168
A33: Budget Summary based on the Final Pricing (Cell#E14 in Executive Summary Tab)
A34: Budget Parameter | D34: Consulting | H34: Design | L34: Analytics | P34: Technology | T34: QA | X34: Del EX
A35: Effort (PM) | D35: 44.5 | H35: 17.6 | L35: 55 | P35: 45 | T35: 16 | X35: 12
A36: Revenue (USD) | D36: =(D35/$AZ$26)*'Executive Summary'!$E$14 -> 200993.68 | H36: =(H35/$AZ$26)*'Executive Summary'!$E$14 -> 79494.128 | L36: =(L35/$AZ$26)*'Executive Summary'!$E$14 -> 248419.15 | P36: =(P35/$AZ$26)*'Executive Summary'!$E$14 -> 203252.03 | T36: =(T35/$AZ$26)*'Executive Summary'!$E$14 -> 72267.389 | X36: =(X35/$AZ$26)*'Executive Summary'!$E$14 -> 54200.542
A40: Budget Break-up by Month
A41: ON/OFF | D41: Month-1 | H41: Month-2 | L41: Month-3 | P41: Month-4 | T41: Month-5 | X41: Month-6 | AB41: Month-7 | AF41: Month-8 | AJ41: Month-9 | AN41: Month-10 | AR41: Month-11 | AV41: Month-12 | AZ41: Total | BA41: Balance
A42: Budget | D42: =(D26/$AZ$26)*'Executive Summary'!$E$14 -> 79042.457 | H42: =(H26/$AZ$26)*'Executive Summary'!$E$14 -> 79042.457 | L42: =(L26/$AZ$26)*'Executive Summary'!$E$14 -> 79042.457 | P42: =(P26/$AZ$26)*'Executive Summary'!$E$14 -> 91237.579 | T42: =(T26/$AZ$26)*'Executive Summary'!$E$14 -> 91237.579 | X42: =(X26/$AZ$26)*'Executive Summary'!$E$14 -> 86720.867 | AB42: =(AB26/$AZ$26)*'Executive Summary'!$E$14 -> 84462.511 | AF42: =(AF26/$AZ$26)*'Executive Summary'!$E$14 -> 84462.511 | AJ42: =(AJ26/$AZ$26)*'Executive Summary'!$E$14 -> 84462.511 | AN42: =(AN26/$AZ$26)*'Executive Summary'!$E$14 -> 84462.511 | AR42: =(AR26/$AZ$26)*'Executive Summary'!$E$14 -> 79945.799 | AV42: =(AV26/$AZ$26)*'Executive Summary'!$E$14 -> 75880.759 | AZ42: =SUM(D42:AY42) -> 1000000
A43: Accrual | AZ43: =SUM(D43:AY43) -> 0 | BA43: =AZ42-AZ43 -> 1000000
A44: Invoice | AZ44: =SUM(D44:AY44) -> 0 | BA44: =AZ42-AZ44 -> 1000000

Sheet Module 3 Cost Guidance
A4: Module 3
B5: Line Item | C5: Cost | D5: Comments
B6: #FTEs | C6: NA
B7: Resource Load Cost (as per resource load plan) | C7: ='Module 3 During-Disaster Integr'!$BB$28 -> 1487808
B8: SG & A, Project Risk Factors & Other Overheads etc. (25%) | C8: =C7*0.15 -> 223171.2
B9: Total Development Cost (sales guidance) | C9: =C7+C8 -> 1710979.2
B11: Integrated Data Engineering Module for all the 3 Hazards | C11: 1539881
B12: During-Disaster Integrated POD for all the 3 Hazards | C12: =C11 -> 1539881
B13: Annual Upkeep & Maintenance | C13: =C12*0.185 -> 284877.98
B16: AWS Cloud Cost | C16: ='Cloud Infra Estimate'!$G$15 -> 463986
B17: Final AWS Cloud Cost (rounded off for minor variations) | C17: =C16 -> 463986
B21: Final Cost Structure
B23: Category | C23: Sub-Category | D23: Year-1 | E23: Year-2 | F23: Year-3 | G23: Total
B24: Integrated Pre-Disaster Module for all the 3 Hazards | C24: One-time Development (professional fee) | D24: =C12 -> 1539881 | G24: =D24 -> 1539881
C25: Annual Upkeep & Maintenance | D25: =C13*0.5 -> 142438.99 | E25: =C13 -> 284877.98 | F25: =C13 -> 284877.98 | G25: =SUM(D25:F25) -> 712194.96
C26: Total | D26: =D24+D25 -> 1682320 | E26: =E25 -> 284877.98 | F26: =F25 -> 284877.98 | G26: =D24*0.275 -> 423467.28
B27: Cloud Infrastructure Costs | C27: AWS Costs | D27: ='Cloud Infra Estimate'!$F$15 -> 353500 | E27: ='Cloud Infra Estimate'!$F$15 -> 353500 | F27: ='Cloud Infra Estimate'!$F$15 -> 353500 | G27: =SUM(D27:F27) -> 1060500
C28: Total | D28: =D27 -> 353500 | E28: =E27 -> 353500 | F28: =F27 -> 353500 | G28: =SUM(D28:F28) -> 1060500
B29: TOTAL | D29: =D26+D28 -> 2035820 | E29: =E26+E28 -> 638377.98 | F29: =F26+F28 -> 638377.98 | G29: =G26+G28 -> 1483967.3

Sheet Module 3.1 During-Disaster Hyb
A1: Activity / Month | D1: Month-1 | H1: Month-2 | L1: Month-3 | P1: Month-4 | T1: Month-5 | X1: Month-6 | AB1: Month-7 | AF1: Month-8 | AJ1: Month-9 | AN1: Month-10 | AR1: Month-11 | AV1: Month-12
A2: Requirements and project planning
A3: Data and methodology review
A4: Workshops with stakeholders
A5: Development
A6: Integration Development (APIs)
A7: Testing (Ground-Truth Data or On-Ground)
A8: UAT and Go-Live
A11: Role / Month | B11: Geography | C11: ON/OFF | D11: Month-1 | H11: Month-2 | L11: Month-3 | P11: Month-4 | T11: Month-5 | X11: Month-6 | AB11: Month-7 | AF11: Month-8 | AJ11: Month-9 | AN11: Month-10 | AR11: Month-11 | AV11: Month-12 | AZ11: Total (mos) | BA11: Rate/Hr | BB11: Total Price
A12: Account Manager | B12: APAC | C12: Offshore | D12: 0.5 | H12: 0.5 | L12: 0.5 | P12: 0.2 | T12: 0.2 | X12: 0.2 | AB12: 0.2 | AF12: 0.2 | AJ12: 0.2 | AN12: 0.2 | AR12: 0.2 | AV12: 0.2 | AZ12: =SUM(D12:AY12) -> 3.3 | BA12: 40 | BB12: =AZ12*BA12*$BB$30 -> 22176
A13: Project Manager | B13: APAC | C13: Offshore | D13: 0.7 | H13: 0.7 | L13: 0.7 | P13: 0.7 | T13: 0.7 | X13: 0.5 | AB13: 0.5 | AF13: 0.5 | AJ13: 0.5 | AN13: 0.5 | AR13: 0.5 | AV13: 0.5 | AZ13: =SUM(D13:AY13) -> 7 | BA13: 40 | BB13: =AZ13*BA13*$BB$30 -> 47040
A14: Data Consultant | B14: APAC | C14: Offshore | D14: 1 | H14: 1 | L14: 1 | P14: 1 | T14: 1 | X14: 1 | AB14: 1 | AF14: 1 | AJ14: 1 | AN14: 1 | AR14: 1 | AV14: 1 | AZ14: =SUM(D14:AY14) -> 12 | BA14: 40 | BB14: =AZ14*BA14*$BB$30 -> 80640
A15: Lead Data Consultant | B15: APAC | C15: Offshore | D15: 1 | H15: 1 | L15: 1 | P15: 1 | T15: 1 | X15: 1 | AB15: 1 | AF15: 1 | AJ15: 1 | AN15: 1 | AR15: 1 | AV15: 1 | AZ15: =SUM(D15:AY15) -> 12 | BA15: 40 | BB15: =AZ15*BA15*$BB$30 -> 80640
A16: UX Design Lead | B16: APAC | C16: Offshore | P16: 1 | T16: 1 | X16: 1 | AB16: 1 | AF16: 1 | AJ16: 1 | AZ16: =SUM(D16:AY16) -> 6 | BA16: 40 | BB16: =AZ16*BA16*$BB$30 -> 40320
A17: UX Designer | B17: APAC | C17: Offshore | P17: 1 | T17: 1 | X17: 1 | AB17: 1 | AF17: 1 | AJ17: 1 | AN17: 1 | AR17: 1 | AV17: 1 | AZ17: =SUM(D17:AY17) -> 9 | BA17: 40 | BB17: =AZ17*BA17*$BB$30 -> 60480
A18: Lead Data Scientist | B18: APAC | C18: Offshore | D18: 2 | H18: 2 | L18: 2 | P18: 2 | T18: 2 | X18: 2 | AB18: 2 | AF18: 2 | AJ18: 2 | AN18: 2 | AR18: 2 | AV18: 2 | AZ18: =SUM(D18:AY18) -> 24 | BA18: 40 | BB18: =AZ18*BA18*$BB$30 -> 161280
A19: Data Scientist | B19: APAC | C19: Offshore | D19: 2 | H19: 2 | L19: 2 | P19: 2 | T19: 2 | X19: 2 | AB19: 2 | AF19: 2 | AJ19: 2 | AN19: 2 | AR19: 2 | AV19: 2 | AZ19: =SUM(D19:AY19) -> 24 | BA19: 40 | BB19: =AZ19*BA19*$BB$30 -> 161280
A20: Technical Lead | B20: APAC | C20: Offshore | D20: 2 | H20: 2 | L20: 2 | P20: 2 | T20: 2 | X20: 1 | AB20: 1 | AF20: 1 | AJ20: 1 | AN20: 1 | AR20: 1 | AV20: 1 | AZ20: =SUM(D20:AY20) -> 17 | BA20: 40 | BB20: =AZ20*BA20*$BB$30 -> 114240
A21: Senior Developer | B21: APAC | C21: Offshore | D21: 2 | H21: 2 | L21: 2 | P21: 2 | T21: 2 | X21: 2 | AB21: 1 | AF21: 1 | AJ21: 1 | AN21: 1 | AR21: 1 | AV21: 1 | AZ21: =SUM(D21:AY21) -> 18 | BA21: 40 | BB21: =AZ21*BA21*$BB$30 -> 120960
A22: Developer | B22: APAC | C22: Offshore | D22: 3 | H22: 3 | L22: 2 | P22: 2 | T22: 2 | X22: 2 | AB22: 2 | AF22: 2 | AJ22: 1 | AN22: 1 | AR22: 1 | AV22: 1 | AZ22: =SUM(D22:AY22) -> 22 | BA22: 40 | BB22: =AZ22*BA22*$BB$30 -> 147840
A23: DevOps Engineer | B23: APAC | C23: Offshore | D23: 1 | H23: 1 | L23: 1 | P23: 1 | AV23: 0.5 | AZ23: =SUM(D23:AY23) -> 4.5 | BA23: 40 | BB23: =AZ23*BA23*$BB$30 -> 30240
A24: QA Tester | B24: APAC | C24: Offshore | T24: 2 | X24: 2 | AB24: 2 | AF24: 2 | AJ24: 2 | AN24: 2 | AR24: 2 | AV24: 2 | AZ24: =SUM(D24:AY24) -> 16 | BA24: 40 | BB24: =AZ24*BA24*$BB$30 -> 107520
B25: APAC | AZ25: =SUM(D25:AY25) -> 0 | BA25: 0 | BB25: =AZ25*BA25*$BB$30 -> 0
A26: Total FTE Man Months | D26: =SUM(D12:D25) -> 15.2 | H26: =SUM(H12:H25) -> 15.2 | L26: =SUM(L12:L25) -> 14.2 | P26: =SUM(P12:P25) -> 15.9 | T26: =SUM(T12:T25) -> 16.9 | X26: =SUM(X12:X25) -> 15.7 | AB26: =SUM(AB12:AB25) -> 14.7 | AF26: =SUM(AF12:AF25) -> 14.7 | AJ26: =SUM(AJ12:AJ25) -> 13.7 | AN26: =SUM(AN12:AN25) -> 12.7 | AR26: =SUM(AR12:AR25) -> 12.7 | AV26: =SUM(AV12:AV25) -> 13.2 | AZ26: =SUM(AZ12:AZ25) -> 174.8 | BB26: =SUM(BB12:BB25) -> 1174656
A27: *Geography is taken directly from Executive Summary sheet. Please update it in Executive Summary sheet to change Geo.
AZ28: Total Billing in USD | BB28: =BB26 -> 1174656
AZ29: Total Billing in INR | BB29: ='Executive Summary'!$E$1*BB28 -> 99845760
AZ30: Billable Hours per Month (assumption) | BB30: 168
A33: Budget Summary based on the Final Pricing (Cell#E14 in Executive Summary Tab)
A34: Budget Parameter | D34: Consulting | H34: Design | L34: Analytics | P34: Technology | T34: QA | X34: Del EX
A35: Effort (PM) | D35: 24 | H35: 15 | L35: 48 | P35: 39 | T35: 16 | X35: 7
A36: Revenue (USD) | D36: =(D35/$AZ$26)*'Executive Summary'!$E$14 -> 137299.77 | H36: =(H35/$AZ$26)*'Executive Summary'!$E$14 -> 85812.357 | L36: =(L35/$AZ$26)*'Executive Summary'!$E$14 -> 274599.54 | P36: =(P35/$AZ$26)*'Executive Summary'!$E$14 -> 223112.13 | T36: =(T35/$AZ$26)*'Executive Summary'!$E$14 -> 91533.181 | X36: =(X35/$AZ$26)*'Executive Summary'!$E$14 -> 40045.767
A40: Budget Break-up by Month
A41: ON/OFF | D41: Month-1 | H41: Month-2 | L41: Month-3 | P41: Month-4 | T41: Month-5 | X41: Month-6 | AB41: Month-7 | AF41: Month-8 | AJ41: Month-9 | AN41: Month-10 | AR41: Month-11 | AV41: Month-12 | AZ41: Total | BA41: Balance
A42: Budget | D42: =(D26/$AZ$26)*'Executive Summary'!$E$14 -> 86956.522 | H42: =(H26/$AZ$26)*'Executive Summary'!$E$14 -> 86956.522 | L42: =(L26/$AZ$26)*'Executive Summary'!$E$14 -> 81235.698 | P42: =(P26/$AZ$26)*'Executive Summary'!$E$14 -> 90961.098 | T42: =(T26/$AZ$26)*'Executive Summary'!$E$14 -> 96681.922 | X42: =(X26/$AZ$26)*'Executive Summary'!$E$14 -> 89816.934 | AB42: =(AB26/$AZ$26)*'Executive Summary'!$E$14 -> 84096.11 | AF42: =(AF26/$AZ$26)*'Executive Summary'!$E$14 -> 84096.11 | AJ42: =(AJ26/$AZ$26)*'Executive Summary'!$E$14 -> 78375.286 | AN42: =(AN26/$AZ$26)*'Executive Summary'!$E$14 -> 72654.462 | AR42: =(AR26/$AZ$26)*'Executive Summary'!$E$14 -> 72654.462 | AV42: =(AV26/$AZ$26)*'Executive Summary'!$E$14 -> 75514.874 | AZ42: =SUM(D42:AY42) -> 1000000
A43: Accrual | AZ43: =SUM(D43:AY43) -> 0 | BA43: =AZ42-AZ43 -> 1000000
A44: Invoice | AZ44: =SUM(D44:AY44) -> 0 | BA44: =AZ42-AZ44 -> 1000000

Sheet Module 4 Scope Map
B2: MODULE 4 | Revised 2-Hazard Scope (Flood + Landslide) - Scope to Effort Map
B3: Source: Straive 'Commercial Proposal: National Multi-Hazard Disaster Monitoring and Decision Support System', Revised Scope of Work. Wildfire analysis removed per client mail of 31 Jul 2026 (Ahmad Yokasano, Paques).
B5: Sec | C5: Scope Area | D5: What is being built | E5: Effort (FTE-mo) | F5: % of Build | G5: Value (USD)
B6: 1 | C6: Flood Hazard Monitoring & Early Action Pipeline | D6: WFLOW_sbm distributed hydrology; HEC-HMS urban flash; HEC-RAS 2D + LISFLOOD-FP inundation; SFINCS river-tide backwater; Siaga trigger logic; hydrograph / WSE / velocity / exposure outputs | E6: 42 | F6: =E6/$E$14 -> 0.21920668 | G6: =E6/$E$14*'Module 4 Flood-Landslide POD'!$BB$28 -> 282240
B7: 2 | C7: Landslide Hazard Monitoring & Early Warning Pipeline | D7: SINMAP/SHALSTAB static FS; TRIGRS/Scoops3D transient pore-water; RAMMS/FLO-2D runout; 4-parameter trigger chain; susceptibility + hourly FS grids + mudflow footprint | E7: 34 | F7: =E7/$E$14 -> 0.17745303 | G7: =E7/$E$14*'Module 4 Flood-Landslide POD'!$BB$28 -> 228480
B8: 3 | C8: Integrated Analytics, Vulnerability Assessment & Network Routing | D8: MCDM + Random Forest / Gradient Boosting vulnerability indexing; NetworkX regency graph extraction (OSM + PUPR, 50 regencies); Dijkstra / A* / RL evacuation routing | E8: 26 | F8: =E8/$E$14 -> 0.13569937 | G8: =E8/$E$14*'Module 4 Flood-Landslide POD'!$BB$28 -> 174720
B9: 4 | C9: Operational Resource & Recovery Estimation Modules | D9: Personnel needs; relief materials; emergency fund estimation; post-disaster recovery / damage classification on satellite & drone imagery | E9: 18 | F9: =E9/$E$14 -> 0.09394572 | G9: =E9/$E$14*'Module 4 Flood-Landslide POD'!$BB$28 -> 120960
B10: 5 | C10: Architectural Data Ingestion & Dissemination Integrity | D10: Ingestion architecture; latency SLA engineering; Pusdatinkom gateways; outbound SMS / inaRISK push; IVR voicebot + WhatsApp/Telegram feedback loop | E10: 24 | F10: =E10/$E$14 -> 0.12526096 | G10: =E10/$E$14*'Module 4 Flood-Landslide POD'!$BB$28 -> 161280
B11: 6 | C11: Hybrid Infrastructure, Deployment & SLA Hardening | D11: On-prem BNPB DC deployment; Jakarta-region cloud burst layer; CI/CD; AES-256 / TLS 1.2+; 99.9% availability engineering | E11: 16 | F11: =E11/$E$14 -> 0.083507307 | G11: =E11/$E$14*'Module 4 Flood-Landslide POD'!$BB$28 -> 107520
B12: - | C12: Command Centre (Pillar 1) Visualisation & UX | D12: Read-only maps, deployment tables, cost charts, hazard overlays, UX research and design system | E12: 14 | F12: =E12/$E$14 -> 0.073068894 | G12: =E12/$E$14*'Module 4 Flood-Landslide POD'!$BB$28 -> 94080
B13: - | C13: Programme Management, QA & UAT | D13: Account and project management, ground-truth validation against KGE >= 0.70 and IoU >= 0.60 quality gates, UAT and go-live | E13: 17.6 | F13: =E13/$E$14 -> 0.091858038 | G13: =E13/$E$14*'Module 4 Flood-Landslide POD'!$BB$28 -> 118272
B14: Total Build Effort | E14: =SUM(E6:E13) -> 191.6 | F14: =SUM(F6:F13) -> 1 | G14: ='Module 4 Flood-Landslide POD'!$BB$28 -> 1287552
B16: Note: value shown is Resource Load Cost (bill value at $40/hr x 168 hrs), before SG&A and before any discount. See 'Module 4 Cost Guidance'.

Sheet Module 4 Flood-Landslide POD
A1: Activity / Month | D1: Month-1 | H1: Month-2 | L1: Month-3 | P1: Month-4 | T1: Month-5 | X1: Month-6 | AB1: Month-7 | AF1: Month-8 | AJ1: Month-9 | AN1: Month-10 | AR1: Month-11 | AV1: Month-12
A2: Requirements, Data Access & Discovery
A3: Data Ingestion & Lakehouse Build (On-Prem)
A4: Flood Modelling Chain Development
A5: Landslide Modelling Chain Development
A6: Integrated Analytics, Vulnerability & Routing
A7: Resource/Recovery Estimation & Dissemination
A8: Ground-Truth Validation & SLA Testing
A9: UAT, Hybrid Deployment & Go-Live
A11: Role / Month | B11: Geography | C11: ON/OFF | D11: Month-1 | H11: Month-2 | L11: Month-3 | P11: Month-4 | T11: Month-5 | X11: Month-6 | AB11: Month-7 | AF11: Month-8 | AJ11: Month-9 | AN11: Month-10 | AR11: Month-11 | AV11: Month-12 | AZ11: Total (mos) | BA11: Rate/Hr | BB11: Total Price
A12: Account Manager | B12: APAC | C12: Offshore | D12: 0.5 | H12: 0.5 | L12: 0.3 | P12: 0.2 | T12: 0.2 | X12: 0.2 | AB12: 0.2 | AF12: 0.2 | AJ12: 0.2 | AN12: 0.2 | AR12: 0.2 | AV12: 0.2 | AZ12: =SUM(D12:AY12) -> 3.1 | BA12: 40 | BB12: =AZ12*BA12*$BB$30 -> 20832
A13: Project Manager | B13: APAC | C13: Offshore | D13: 1 | H13: 1 | L13: 1 | P13: 1 | T13: 1 | X13: 1 | AB13: 1 | AF13: 1 | AJ13: 1 | AN13: 1 | AR13: 1 | AV13: 1 | AZ13: =SUM(D13:AY13) -> 12 | BA13: 40 | BB13: =AZ13*BA13*$BB$30 -> 80640
A14: Data Consultant | B14: APAC | C14: Offshore | D14: 1 | H14: 1 | L14: 1 | P14: 1 | T14: 1 | X14: 1 | AB14: 1 | AF14: 0.5 | AJ14: 0.5 | AN14: 0.5 | AR14: 0.5 | AV14: 0.5 | AZ14: =SUM(D14:AY14) -> 9.5 | BA14: 40 | BB14: =AZ14*BA14*$BB$30 -> 63840
A15: Lead Data Consultant | B15: APAC | C15: Offshore | D15: 1 | H15: 1 | L15: 1 | P15: 1 | T15: 1 | X15: 1 | AB15: 1 | AF15: 1 | AJ15: 1 | AN15: 1 | AR15: 1 | AV15: 1 | AZ15: =SUM(D15:AY15) -> 12 | BA15: 40 | BB15: =AZ15*BA15*$BB$30 -> 80640
A16: UX Design Lead | B16: APAC | C16: Offshore | L16: 1 | P16: 1 | T16: 1 | X16: 1 | AB16: 0.5 | AF16: 0.5 | AJ16: 0.5 | AN16: 0.5 | AZ16: =SUM(D16:AY16) -> 6 | BA16: 40 | BB16: =AZ16*BA16*$BB$30 -> 40320
A17: UX Designer | B17: APAC | C17: Offshore | L17: 1 | P17: 1 | T17: 1 | X17: 1 | AB17: 1 | AF17: 1 | AJ17: 1 | AN17: 0.5 | AR17: 0.5 | AZ17: =SUM(D17:AY17) -> 8 | BA17: 40 | BB17: =AZ17*BA17*$BB$30 -> 53760
A18: Lead Data Scientist | B18: APAC | C18: Offshore | D18: 1 | H18: 1 | L18: 2 | P18: 2 | T18: 2 | X18: 2 | AB18: 2 | AF18: 2 | AJ18: 2 | AN18: 2 | AR18: 1 | AV18: 1 | AZ18: =SUM(D18:AY18) -> 20 | BA18: 40 | BB18: =AZ18*BA18*$BB$30 -> 134400
A19: Data Scientist | B19: APAC | C19: Offshore | D19: 1 | H19: 2 | L19: 3 | P19: 4 | T19: 4 | X19: 4 | AB19: 4 | AF19: 4 | AJ19: 3 | AN19: 3 | AR19: 2 | AV19: 2 | AZ19: =SUM(D19:AY19) -> 36 | BA19: 40 | BB19: =AZ19*BA19*$BB$30 -> 241920
A20: Technical Lead | B20: APAC | C20: Offshore | D20: 1 | H20: 1 | L20: 1 | P20: 1 | T20: 1 | X20: 1 | AB20: 1 | AF20: 1 | AJ20: 1 | AN20: 1 | AR20: 1 | AV20: 1 | AZ20: =SUM(D20:AY20) -> 12 | BA20: 40 | BB20: =AZ20*BA20*$BB$30 -> 80640
A21: Senior Developer | B21: APAC | C21: Offshore | D21: 1 | H21: 2 | L21: 2 | P21: 2 | T21: 2 | X21: 2 | AB21: 2 | AF21: 2 | AJ21: 2 | AN21: 2 | AR21: 1 | AV21: 1 | AZ21: =SUM(D21:AY21) -> 21 | BA21: 40 | BB21: =AZ21*BA21*$BB$30 -> 141120
A22: Developer | B22: APAC | C22: Offshore | H22: 1 | L22: 2 | P22: 2 | T22: 3 | X22: 3 | AB22: 3 | AF22: 3 | AJ22: 3 | AN22: 2 | AR22: 2 | AV22: 1 | AZ22: =SUM(D22:AY22) -> 25 | BA22: 40 | BB22: =AZ22*BA22*$BB$30 -> 168000
A23: DevOps Engineer | B23: APAC | C23: Offshore | D23: 1 | H23: 1 | L23: 1 | P23: 1 | T23: 1 | X23: 1 | AB23: 1 | AF23: 1 | AJ23: 1 | AN23: 1 | AR23: 1 | AV23: 1 | AZ23: =SUM(D23:AY23) -> 12 | BA23: 40 | BB23: =AZ23*BA23*$BB$30 -> 80640
A24: QA Tester | B24: APAC | C24: Offshore | P24: 1 | T24: 1 | X24: 1 | AB24: 2 | AF24: 2 | AJ24: 2 | AN24: 2 | AR24: 2 | AV24: 2 | AZ24: =SUM(D24:AY24) -> 15 | BA24: 40 | BB24: =AZ24*BA24*$BB$30 -> 100800
B25: APAC | AZ25: =SUM(D25:AY25) -> 0 | BA25: 0 | BB25: =AZ25*BA25*$BB$30 -> 0
A26: Total FTE Man Months | D26: =SUM(D12:D25) -> 8.5 | H26: =SUM(H12:H25) -> 11.5 | L26: =SUM(L12:L25) -> 16.3 | P26: =SUM(P12:P25) -> 18.2 | T26: =SUM(T12:T25) -> 19.2 | X26: =SUM(X12:X25) -> 19.2 | AB26: =SUM(AB12:AB25) -> 19.7 | AF26: =SUM(AF12:AF25) -> 19.2 | AJ26: =SUM(AJ12:AJ25) -> 18.2 | AN26: =SUM(AN12:AN25) -> 16.7 | AR26: =SUM(AR12:AR25) -> 13.2 | AV26: =SUM(AV12:AV25) -> 11.7 | AZ26: =SUM(AZ12:AZ25) -> 191.6 | BB26: =SUM(BB12:BB25) -> 1287552
A27: *Geography is taken directly from Executive Summary sheet. Please update it in Executive Summary sheet to change Geo.
AZ28: Total Billing in USD | BB28: =BB26 -> 1287552
AZ29: Total Billing in INR | BB29: ='Executive Summary'!$E$1*BB28 -> 109441920
AZ30: Billable Hours per Month (assumption) | BB30: 168
A33: Budget Summary based on the Final Pricing (Cell#E14 in Executive Summary Tab)
A34: Budget Parameter | D34: Consulting | H34: Design | L34: Analytics | P34: Technology | T34: QA | X34: Del EX
A35: Effort (PM) | D35: 24.6 | H35: 14 | L35: 56 | P35: 70 | T35: 15 | X35: 12
A36: Revenue (USD) | D36: =(D35/$AZ$26)*'Executive Summary'!$E$14 -> 128392.48 | H36: =(H35/$AZ$26)*'Executive Summary'!$E$14 -> 73068.894 | L36: =(L35/$AZ$26)*'Executive Summary'!$E$14 -> 292275.57 | P36: =(P35/$AZ$26)*'Executive Summary'!$E$14 -> 365344.47 | T36: =(T35/$AZ$26)*'Executive Summary'!$E$14 -> 78288.1 | X36: =(X35/$AZ$26)*'Executive Summary'!$E$14 -> 62630.48
A40: Budget Break-up by Month
A41: ON/OFF | D41: Month-1 | H41: Month-2 | L41: Month-3 | P41: Month-4 | T41: Month-5 | X41: Month-6 | AB41: Month-7 | AF41: Month-8 | AJ41: Month-9 | AN41: Month-10 | AR41: Month-11 | AV41: Month-12 | AZ41: Total | BA41: Balance
A42: Budget | D42: =(D26/$AZ$26)*'Executive Summary'!$E$14 -> 44363.257 | H42: =(H26/$AZ$26)*'Executive Summary'!$E$14 -> 60020.877 | L42: =(L26/$AZ$26)*'Executive Summary'!$E$14 -> 85073.069 | P42: =(P26/$AZ$26)*'Executive Summary'!$E$14 -> 94989.562 | T42: =(T26/$AZ$26)*'Executive Summary'!$E$14 -> 100208.77 | X42: =(X26/$AZ$26)*'Executive Summary'!$E$14 -> 100208.77 | AB42: =(AB26/$AZ$26)*'Executive Summary'!$E$14 -> 102818.37 | AF42: =(AF26/$AZ$26)*'Executive Summary'!$E$14 -> 100208.77 | AJ42: =(AJ26/$AZ$26)*'Executive Summary'!$E$14 -> 94989.562 | AN42: =(AN26/$AZ$26)*'Executive Summary'!$E$14 -> 87160.752 | AR42: =(AR26/$AZ$26)*'Executive Summary'!$E$14 -> 68893.528 | AV42: =(AV26/$AZ$26)*'Executive Summary'!$E$14 -> 61064.718 | AZ42: =SUM(D42:AY42) -> 1000000
A43: Accrual | AZ43: =SUM(D43:AY43) -> 0 | BA43: =AZ42-AZ43 -> 1000000
A44: Invoice | AZ44: =SUM(D44:AY44) -> 0 | BA44: =AZ42-AZ44 -> 1000000

Sheet Module 4 Cost Guidance
B2: MODULE 4 | Cost Guidance - Integrated Flood & Landslide (2 Hazards)
B4: Line Item | C4: Cost | D4: Comments
B5: #FTEs (peak / average) | C5: ='Module 4 Flood-Landslide POD'!$AZ$26/12 -> 15.966667 | D5: Average FTE across the 12-month build
B6: Resource Load Cost (as per resource load plan) | C6: ='Module 4 Flood-Landslide POD'!$BB$28 -> 1287552 | D6: 191.6 FTE-months @ $40/hr x 168 hrs
B7: SG & A, Project Risk Factors & Other Overheads etc. (15%) | C7: =C6*0.15 -> 193132.8 | D7: 15% - the rate actually applied in Modules 1-3
B8: Total Development Cost (sales guidance) | C8: =C6+C7 -> 1480684.8 | D8: Sales-guidance price before any discount
B9: Discount applied to reach offer price | C9: 0.1 | D9: 10% - the convention used on Module 3
B10: Integrated Flood & Landslide Module (2 Hazards) - one-time | C10: =C8*(1-C9) -> 1332616.3 | D10: Bottom-up one-time professional fee
B12: Support & Maintenance Pod (24x5 shared coverage, annual)
B13: Role | C13: FTE | D13: Months | E13: FTE-Months | F13: Scope of cover
B14: Support / Platform Lead | C14: 0.25 | D14: 12 | E14: =C14*D14 -> 3 | F14: Single point of accountability, SLA reporting, release governance
B15: DevOps / SRE (24x5 shared) | C15: 0.75 | D15: 12 | E15: =C15*D15 -> 9 | F15: Availability >= 99.9%, latency SLA assurance, incident response, patching
B16: Data Engineer | C16: 0.75 | D16: 12 | E16: =C16*D16 -> 9 | F16: Ingestion pipeline break-fix, feed changes (BMKG / LAPAN / IoT), data quality
B17: Data Scientist | C17: 0.4 | D17: 12 | E17: =C17*D17 -> 4.8 | F17: Model drift monitoring, threshold recalibration (I-D curves, FS), seasonal retraining
B18: Application Developer | C18: 0.4 | D18: 12 | E18: =C18*D18 -> 4.8 | F18: Command Centre and dissemination-layer break-fix and minor enhancements
B19: QA Engineer | C19: 0.2 | D19: 12 | E19: =C19*D19 -> 2.4 | F19: Regression testing on releases, SLA and output quality verification
B20: Support Pod Total | C20: =SUM(C14:C19) -> 2.75 | E20: =SUM(E14:E19) -> 33
B21: S&M Resource Load Cost (annual) | C21: =E20*'Module 4 Flood-Landslide POD'!$BB$30*40 -> 221760
B22: SG & A and overheads (15%) | C22: =C21*0.15 -> 33264
B23: S&M sales guidance (annual) | C23: =C21+C22 -> 255024
B24: Annual Support & Maintenance - offer price | C24: =C23*(1-$C$9) -> 229521.6
B26: Hybrid Infrastructure (annual, recurring) | C26: ='Module 4 Hybrid Infra'!$F$17 -> 96500 | D26: Jakarta public cloud only - on-prem BoQ excluded
B29: Final Cost Structure (bottom-up)
B31: Category | C31: Sub-Category | D31: Year-1 | E31: Year-2 | F31: Year-3 | G31: Total
B32: Integrated Flood & Landslide Module (2 Hazards) | C32: One-time Development (professional fee) | D32: =$C$10 -> 1332616.3 | G32: =SUM(D32:F32) -> 1332616.3
C33: Annual Support & Maintenance | E33: =$C$24 -> 229521.6 | F33: =$C$24 -> 229521.6 | G33: =SUM(D33:F33) -> 459043.2
C34: Total | D34: =SUM(D32:D33) -> 1332616.3 | E34: =SUM(E32:E33) -> 229521.6 | F34: =SUM(F32:F33) -> 229521.6 | G34: =SUM(D34:F34) -> 1791659.5
B35: Hybrid Infrastructure Costs | C35: Hybrid Infrastructure (recurring) | D35: =$C$26 -> 96500 | E35: =$C$26 -> 96500 | F35: =$C$26 -> 96500 | G35: =SUM(D35:F35) -> 289500
C36: Total | D36: =SUM(D35:D35) -> 96500 | E36: =SUM(E35:E35) -> 96500 | F36: =SUM(F35:F35) -> 96500 | G36: =SUM(D36:F36) -> 289500
B37: TOTAL | D37: =D34+D36 -> 1429116.3 | E37: =E34+E36 -> 326021.6 | F37: =F34+F36 -> 326021.6 | G37: =G34+G36 -> 2081159.5

Sheet Module 4 Hybrid Infra
B2: MODULE 4 | Hybrid Infrastructure Estimate (Annual, Recurring)
B3: Section 6 of the revised proposal moves the deployment from pure AWS to a Hybrid-Cloud architecture: on-premise BNPB Data Centre plus a Jakarta-region public cloud burst layer. Only the cloud layer sits in Straive's recurring price.
B5: A. Jakarta-Region Public Cloud - IN Straive recurring price
B6: Layer | C6: Component | D6: Deployment | E6: Purpose | F6: Annual Cost (USD)
B7: Compute | C7: Elastic GPU compute (AI/ML training & burst inference) | D7: Jakarta Public Cloud | E7: Seasonal burst capacity during peak hazard events | F7: 26000
B8: Compute | C8: Managed Kubernetes / container orchestration | D8: Jakarta Public Cloud | E8: Burst inference and modelling-chain orchestration | F8: 11000
B9: Storage | C9: Object storage extension & archive tier | D9: Jakarta Public Cloud | E9: Overflow beyond on-prem 241 TB, long-term hazard archive | F9: 13500
B10: Data | C10: Geospatial data egress & processing | D10: Jakarta Public Cloud | E10: Sentinel-1 SAR, GLO-30/FABDEM, WorldPop, OSM pulls | F10: 9000
B11: Streaming | C11: Streaming & IoT telemetry ingest | D11: Jakarta Public Cloud | E11: Peak-event sensor, radar and rain-gauge throughput | F11: 7500
B12: DevOps | C12: Monitoring, logging and tracing | D12: Jakarta Public Cloud | E12: Assurance of <= 20 min end-to-end EAS latency SLA | F12: 6000
B13: Security | C13: Secrets manager / KMS / security tooling | D13: Jakarta Public Cloud | E13: AES-256 at rest, TLS 1.2+ in transit, key custody | F13: 4500
B14: Networking | C14: API gateway, load balancer and CDN | D14: Jakarta Public Cloud | E14: Dissemination APIs, webhooks, Command Centre delivery | F14: 7000
B15: Resilience | C15: Backup and DR replication | D15: Jakarta Public Cloud | E15: Off-site replication of on-prem data lake | F15: 6500
B16: Networking | C16: On-prem to cloud interconnect | D16: Hybrid | E16: Dedicated link between BNPB DC and Jakarta region | F16: 5500
B17: Total Hybrid Infrastructure (Annual, Recurring) | F17: =SUM(F7:F16) -> 96500
B19: B. On-Premise BNPB Data Centre - EXCLUDED, client-supplied (BoQ reference)
C20: Module / Component | D20: Specification & Quantity Details | F20: Straive Cost
C21: Ingestion | D21: 5 servers sized to handle ~1.7 TB/day | F21: 0
C22: Storage | D22: ~241 TB NAS/SAN with 90-day retention and 30% buffer | F22: 0
C23: ETL / Data Engineering | D23: 4 Spark/Airflow servers | F23: 0
C24: AI/ML Inference | D24: 2 GPU servers (NVIDIA T4 or A2) for low-latency predictions | F24: 0
C25: Data Centre Facilities | D25: Rack space, power, cooling, LAN/WAN, physical security | F25: 0
B26: Total On-Premise in Straive price (hardware supplied by client) | F26: =SUM(F21:F25) -> 0
B28: C. Explicit Exclusions - must appear in the commercial
B29: 1 | C29: On-premise hardware procurement, installation and setup - performed by the client's infrastructure partner (Paques Team) per Section 8 Technical & Operational Assumptions.
B30: 2 | C30: SMS, IVR and OTT broadcast carrier charges for the 170-180 million active number population - borne by BNPB / Pusdatinkom and the participating Telcos.
B31: 3 | C31: Third-party commercial data licences (commercial satellite tasking, proprietary basemaps, paid weather feeds).
B32: 4 | C32: BNPB data centre facilities, power, cooling and physical security.
B33: 5 | C33: Any features outside the defined scope - chargeable on a Time & Material basis.

Sheet Module 4 Commercial Recon
B2: MODULE 4 | Bottom-Up Estimate vs Published Option 2 Commercial
B3: Published figures are taken from Section 7 'Commercial Terms' of the Straive proposal (Option 2 - 2 Hazards led by Straive: Flood & Landslide). Bottom-up figures are built from the Module 4 resource load plan and hybrid infra sheet.
B5: Commercial Line | C5: Bottom-Up (this workbook) | D5: Published Option 2 | E5: Variance (USD) | F5: Variance % | G5: Read-out
B6: AI Solution Development + Data Engineering (one-time) | C6: ='Module 4 Cost Guidance'!$C$10 -> 1332616.3 | D6: 1176597 | E6: =C6-D6 -> 156019.32 | F6: =IF(D6=0,"",E6/D6) -> 0.13260217 | G6: Published price is under the bottom-up build by ~13%. Either descope, or book the difference as a deliberate strategic discount.
B7: IT Infrastructure (annual, recurring) | C7: ='Module 4 Cost Guidance'!$C$26 -> 96500 | D7: 91974 | E7: =C7-D7 -> 4526 | F7: =IF(D7=0,"",E7/D7) -> 0.049209559 | G7: Broadly aligned. Confirm the cloud sizing against a live calculator.
B8: Support & Maintenance (annual, recurring) | C8: ='Module 4 Cost Guidance'!$C$24 -> 229521.6 | D8: 199795 | E8: =C8-D8 -> 29726.6 | F8: =IF(D8=0,"",E8/D8) -> 0.14878551 | G8: Published S&M funds ~2.4 shared FTE against a 2.75 FTE pod for a 99.9% / 24x5 commitment. Thinnest line in the deal.
B10: Year-wise position
B11: Year 1 (build + infra) | C11: ='Module 4 Cost Guidance'!$D$37 -> 1429116.3 | D11: 1268571 | E11: =C11-D11 -> 160545.32 | F11: =E11/D11 -> 0.12655604
B12: Year 2 (infra + S&M) | C12: ='Module 4 Cost Guidance'!$E$37 -> 326021.6 | D12: 291769 | E12: =C12-D12 -> 34252.6 | F12: =E12/D12 -> 0.1173963
B13: Year 3 (infra + S&M) | C13: ='Module 4 Cost Guidance'!$F$37 -> 326021.6 | D13: 291769 | E13: =C13-D13 -> 34252.6 | F13: =E13/D13 -> 0.1173963
B14: 3-Year Total Contract Value | C14: ='Module 4 Cost Guidance'!$G$37 -> 2081159.5 | D14: 1852109 | E14: =C14-D14 -> 229050.52 | F14: =E14/D14 -> 0.12367011
B16: Discount position against sales guidance
B17: Total Development Cost (sales guidance) | C17: ='Module 4 Cost Guidance'!$C$8 -> 1480684.8 | E17: Full guidance price before discount
B18: Bottom-up offer price (10% discount) | C18: ='Module 4 Cost Guidance'!$C$10 -> 1332616.3 | D18: =1-C18/C17 -> 0.1 | E18: The Module 3 convention
B19: Published Option 2 price | C19: 1176597 | D19: =1-C19/C17 -> 0.2053697 | E19: Embeds roughly twice the intended discount
B20: Additional discount embedded in published price | C20: =C18-C19 -> 156019.32 | D20: =D19-D18 -> 0.1053697 | E20: Approve this explicitly, or recover it via scope
B22: Levers to close the gap
B23: 1 | C23: Hold the published price and book the delta as an approved strategic discount - this is a New Win and the Executive Summary already flags Approval Needed = YES.
B24: 2 | C24: Reduce Year-1 build scope: Section 4 (Resource & Recovery Estimation, 18.0 FTE-months) is the most severable block and is not part of the Early Action critical path.
B25: 3 | C25: Move the citizen feedback loop (IVR voicebot, WhatsApp/Telegram) in Section 5.2 to a Phase 2 change request on T&M.
B26: 4 | C26: Re-price S&M at the published number but cut the commitment to 12x5 with an on-call rota, rather than 24x5 against a 99.9% SLA.
B27: 5 | C27: Confirm on-prem BoQ hardware exclusion in writing before signature - if it lands in Straive scope the gap widens materially.

Sheet Cloud Infra Estimate
A1: AWS Resource Estimate
A3: Service Category | B3: Service Type | C3: Region | D3: Description | E3: Estimated Annual Cost for Engineering POD (USD) | F3: Estimated Annual Cost for Pre-Disaster Integrated POD (USD) | G3: Estimated Annual Cost for During-Disaster Integrated POD (USD)
A4: Web | B4: Amazon CloudSearch or OpenSearch | C4: Asia Pacific (Jakarta) | D4: Search interface for hazard metadata, incidents, historical events | E4: 18000 | F4: 22000 | G4: 24000
A5: Compute | B5: Amazon EKS (Kubernetes Service) | C5: Asia Pacific (Jakarta) | D5: Container orchestration for ML services and real-time APIs | E5: 32000 | F5: 40000 | G5: 50000
A6: DevOps | B6: Amazon CloudWatch + X-Ray | C6: Asia Pacific (Jakarta) | D6: Monitoring, logging, and tracing across services | E6: 15000 | F6: 10000 | G6: 20000
A7: Security | B7: AWS Secrets Manager / KMS | C7: Asia Pacific (Jakarta) | D7: Securing credentials, API keys, model secrets | E7: 10000 | F7: 7000 | G7: 10000
A8: Developer Tools | B8: AWS AppConfig + CodePipeline | C8: Asia Pacific (Jakarta) | D8: Manage app configurations, model toggles, feature flags | E8: 8000 | F8: 10000 | G8: 12000
A9: Networking | B9: AWS Application Load Balancer (ALB) | C9: Asia Pacific (Jakarta) | D9: Routing real-time traffic for disaster alert APIs | E9: 10000 | F9: 12000 | G9: 16000
A10: Compute | B10: Auto Scaling with EC2 Spot Instances | C10: Asia Pacific (Jakarta) | D10: Scale compute for training/inference workloads | E10: 35000 | F10: 46000 | G10: 56000
A11: AI | B11: Amazon SageMaker (Core ML) | C11: Asia Pacific (Jakarta) | D11: Model training & inference for hazard prediction | E11: 28000 | F11: 48000 | G11: 70000
A12: AI | B12: SageMaker Geospatial Capabilities | C12: Asia Pacific (Jakarta) | D12: Analyze satellite imagery and geospatial risk for flood/fire/landslide | E12: 30000 | F12: 70000 | G12: 85000
A13: AI | B13: AWS IoT + Kinesis (Real-time Feeds) | C13: Asia Pacific (Jakarta) | D13: Ingest and process sensor/weather feeds for live alerts | E13: 15000 | F13: 55000 | G13: 85000
A14: Front-End | B14: AWS Amplify + MapLibre/Mapbox GL JS | C14: Asia Pacific (Jakarta) | D14: Dashboard with satellite map overlays, historical and live hazard visualizations | E14: 15000 | F14: 33500 | G14: 35986
A15: Total Cost Estimates | E15: =SUM(E4:E14) -> 216000 | F15: =SUM(F4:F14) -> 353500 | G15: =SUM(G4:G14) -> 463986

Sheet Assumptions
A1: Assumptions
A2: This estimate is based on the assumptions that roughly data processing is involved daily consisting of the following type of data sources. Only relevant data sources for each use case will be considered. Additional Data sources aren't included as part of this estimate.
A3: Includes either fully on-prem, cloud or hybrid deployments as needed by the client or partner
A4: Any Change Requests to the solution features will be charged on a T&M (Time & Material) basis
A5: Solution Development - Includes model dev, integration dev and support to set up the solution within client infrastructure
A6: Support & Maintenance : 24X5 with shared staffed coverage. Includes the upkeep, break-fix of the data engineering modules along with SLA adherence and performance optimization of the system
A7: SLAs have been discussed in detail in the appropriate section of this proposal. Slide Name - SLAs, RACI Matrix – Support & Maintenance Overview
A8: **IT Infrastructure includes solution hosting, storage, environments, database, networking, compute, security for the Data Management Module ONLY
