Workbook

Sheet Token Breakdown
A1: Per-Record Token Estimate
A3: Component | B3: Tokens | C3: Notes
A4: Instruction prompt | B4: 480 | C4: The verification prompt, sent once per call
A5: Row data (21 columns) | B5: 125 | C5: Average row text size from Issuer_1.xlsx
A6: Web fetches (~2.5 pages × 5K tokens) | B6: 12500 | C6: Source URL + official site + cross-check
A7: Tool-use overhead | B7: 800 | C7: Tool definitions and result framing for web_search/web_fetch
A8: Input total | B8: =SUM(B4:B7) -> 13905 | C8: Sum of input components
A10: Visible output (11 columns) | B10: 70 | C10: The actual verification fields emitted
A11: Reasoning / thinking | B11: 1000 | C11: Internal chain-of-thought during research
A12: Output total | B12: =SUM(B10:B11) -> 1070 | C12: Sum of output components

Sheet Cost Matrix
A1: API Cost — Current Anthropic Pricing (May 2026)
A3: Pricing per 1M tokens
A4: Model | B4: Input ($/1M) | C4: Output ($/1M)
A5: Opus 4.7 | B5: 5 | C5: 25
A6: Sonnet 4.6 | B6: 3 | C6: 15
A7: Haiku 4.5 | B7: 1 | C7: 5
A10: Estimated Cost
A11: Model | B11: 1 record | C11: 100 records | D11: 100 records (Batch API, 50% off)
A12: Opus 4.7 | B12: ='Token Breakdown'!B8/1000000*5+'Token Breakdown'!B12/1000000*25 -> 0.096275 | C12: =100*('Token Breakdown'!B8/1000000*5+'Token Breakdown'!B12/1000000*25) -> 9.6275 | D12: =0.5*100*('Token Breakdown'!B8/1000000*5+'Token Breakdown'!B12/1000000*25) -> 4.81375
A13: Sonnet 4.6 | B13: ='Token Breakdown'!B8/1000000*3+'Token Breakdown'!B12/1000000*15 -> 0.057765 | C13: =100*('Token Breakdown'!B8/1000000*3+'Token Breakdown'!B12/1000000*15) -> 5.7765 | D13: =0.5*100*('Token Breakdown'!B8/1000000*3+'Token Breakdown'!B12/1000000*15) -> 2.88825
A14: Haiku 4.5 | B14: ='Token Breakdown'!B8/1000000*1+'Token Breakdown'!B12/1000000*5 -> 0.019255 | C14: =100*('Token Breakdown'!B8/1000000*1+'Token Breakdown'!B12/1000000*5) -> 1.9255 | D14: =0.5*100*('Token Breakdown'!B8/1000000*1+'Token Breakdown'!B12/1000000*5) -> 0.96275

Sheet Sensitivity Range
A1: Cost Sensitivity — varies with web-research depth
A3: Scenario assumptions
A4: Scenario | B4: Input tokens / row | C4: Output tokens / row | D4: Description
A5: Low end | B5: 6000 | C5: 800 | D5: Source URL works, one fetch, short page
A6: Realistic (used above) | B6: 13900 | C6: 1070 | D6: 2-3 fetches, average page length
A7: High end | B7: 25000 | C7: 1500 | D7: Multiple fetches, long PDFs, retries
A10: Cost per record
A11: Scenario | B11: Opus 4.7 | C11: Sonnet 4.6 | D11: Haiku 4.5
A12: Low end | B12: =B5/1000000*5+C5/1000000*25 -> 0.05 | C12: =B5/1000000*3+C5/1000000*15 -> 0.03 | D12: =B5/1000000*1+C5/1000000*5 -> 0.01
A13: Realistic (used above) | B13: =B6/1000000*5+C6/1000000*25 -> 0.09625 | C13: =B6/1000000*3+C6/1000000*15 -> 0.05775 | D13: =B6/1000000*1+C6/1000000*5 -> 0.01925
A14: High end | B14: =B7/1000000*5+C7/1000000*25 -> 0.1625 | C14: =B7/1000000*3+C7/1000000*15 -> 0.0975 | D14: =B7/1000000*1+C7/1000000*5 -> 0.0325
A17: Cost per 100 records
A18: Scenario | B18: Opus 4.7 | C18: Sonnet 4.6 | D18: Haiku 4.5
A19: Low end | B19: =100*(B5/1000000*5+C5/1000000*25) -> 5 | C19: =100*(B5/1000000*3+C5/1000000*15) -> 3 | D19: =100*(B5/1000000*1+C5/1000000*5) -> 1
A20: Realistic (used above) | B20: =100*(B6/1000000*5+C6/1000000*25) -> 9.625 | C20: =100*(B6/1000000*3+C6/1000000*15) -> 5.775 | D20: =100*(B6/1000000*1+C6/1000000*5) -> 1.925
A21: High end | B21: =100*(B7/1000000*5+C7/1000000*25) -> 16.25 | C21: =100*(B7/1000000*3+C7/1000000*15) -> 9.75 | D21: =100*(B7/1000000*1+C7/1000000*5) -> 3.25

Sheet Notes & Assumptions
A1: Notes & Assumptions
A3: Token estimation method
A4: • 1 token ≈ 4 characters of English / structured text (industry rule of thumb).
A5: • Row data tokens measured from the actual 125 rows in Issuer_1.xlsx (avg ~497 chars / row).
A6: • Web-fetch tokens assume ~5,000 tokens per fetched page after HTML extraction,
A7: and ~2.5 fetches per row (source URL + the company's official site + a cross-check).
A8: • Reasoning/thinking tokens (~1,000 / row) reflect extended-thinking output during
A9: research; you can disable extended thinking to cut this to ~100 tokens.
A11: Pricing source
A12: • Anthropic public API pricing as of May 2026:
A13: Opus 4.7 — $5 input / $25 output per 1M tokens
A14: Sonnet 4.6 — $3 input / $15 output per 1M tokens
... A32: • Opus 4.7 best for cases needing the highest precision on ambiguous matches.
